{
    "intents": [
      {"tag": "goodbye",
         "patterns": ["Bye", "See you later", "Goodbye", "Nice chatting to you, bye", "Till next time"],
         "responses": ["See you!", "Goodbye!", "Have a nice day!", "Bye!"]
        },
        {"tag": "thanks",
         "patterns": ["Thanks", "Thank you", "That's helpful", "Thank's a lot!"],
         "responses": ["You're welcome!", "Anytime!", "Glad I could help!"]
        },
        {"tag": "options",
         "patterns": ["What can you do?", "What services do you offer?", "What are my options?"],
         "responses": ["I can help you with a variety of things. Just let me know what you need!", "I'm here to assist you with whatever you need. Just tell me what you're looking for!", "I can do a lot of things, from answering questions to making reservations. What can I help you with?"]
        },
        {"tag": "name",
         "patterns": ["What's your name?", "What are you called?", "Who are you?"],
         "responses": ["My name is ChatBot!", "I'm ChatBot! Nice to meet you!", "I go by ChatBot!"]
        }
    ]
}